[
  {
    "folder": "illinois",
    "route": "/illinois-car-service",
    "layoutFile": "IllinoisLayout",
    "homeConst": "ILLINOIS_HOME",
    "cssPrefix": "il",
    "regionName": "Illinois",
    "heroLine1": "Premium Illinois",
    "heroAirports": "ORD, Midway or downtown Chicago",
    "docTitle": "Reliable Illinois Car Service for Airports and Long Distance Travel | Urban Elite Limo",
    "navLabel": "Illinois Car Service"
  },
  {
    "folder": "ohare-intl-airport-ord-limo-service",
    "route": "/illinois-car-service/ohare-intl-airport-ord-limo-service",
    "layoutFile": "OhareOrdLimoLayout",
    "homeConst": "OHARE_ORD_LIMO_HOME",
    "cssPrefix": "il-ord-limo",
    "regionName": "O'Hare Intl Airport (ORD) Limo",
    "heroLine1": "O'Hare Intl Airport (ORD) Limo",
    "heroAirports": "O'Hare (ORD) terminals and Chicago",
    "docTitle": "O'Hare Intl Airport (ORD) Limo Service | Urban Elite Limo",
    "navLabel": "O'Hare Intl Airport (ORD) Limo Service"
  },
  {
    "folder": "ohare-intl-airport-ord-car-service",
    "route": "/illinois-car-service/ohare-intl-airport-ord-car-service",
    "layoutFile": "OhareOrdCarLayout",
    "homeConst": "OHARE_ORD_CAR_HOME",
    "cssPrefix": "il-ord-car",
    "regionName": "O'Hare Intl Airport (ORD) Car",
    "heroLine1": "O'Hare Intl Airport (ORD) Car",
    "heroAirports": "O'Hare (ORD) and the greater Chicago area",
    "docTitle": "O'Hare Intl Airport (ORD) Car Service | Urban Elite Limo",
    "navLabel": "O'Hare Intl Airport (ORD) Car Service"
  },
  {
    "folder": "chicago-chauffeur-service",
    "route": "/illinois-car-service/chicago-chauffeur-service",
    "layoutFile": "ChicagoChauffeurLayout",
    "homeConst": "CHICAGO_CHAUFFEUR_HOME",
    "cssPrefix": "il-chi-chauff",
    "regionName": "Chicago Chauffeur",
    "heroLine1": "Chicago Chauffeur",
    "heroAirports": "Chicago business districts and airports",
    "docTitle": "Chicago Chauffeur Service | Urban Elite Limo",
    "navLabel": "Chicago Chauffeur Service"
  },
  {
    "folder": "chicago-airport-car-service",
    "route": "/illinois-car-service/chicago-airport-car-service",
    "layoutFile": "ChicagoAirportCarLayout",
    "homeConst": "CHICAGO_AIRPORT_CAR_HOME",
    "cssPrefix": "il-chi-airport",
    "regionName": "Chicago Airport Car",
    "heroLine1": "Chicago Airport Car",
    "heroAirports": "ORD, Midway and Chicago airports",
    "docTitle": "Chicago Airport Car Service | Urban Elite Limo",
    "navLabel": "Chicago Airport Car Service"
  },
  {
    "folder": "chicago-limo-service",
    "route": "/illinois-car-service/chicago-limo-service",
    "layoutFile": "ChicagoLimoLayout",
    "homeConst": "CHICAGO_LIMO_HOME",
    "cssPrefix": "il-chi-limo",
    "regionName": "Chicago Limo",
    "heroLine1": "Chicago Limo",
    "heroAirports": "Chicago events, airports and special occasions",
    "docTitle": "Chicago Limo Service | Urban Elite Limo",
    "navLabel": "Chicago Limo Service"
  }
]